spi_pack/__init__.py
spi_pack/spi_functions.py
spi_pack-0.3.4.dist-info/METADATA
spi_pack-0.3.4.dist-info/WHEEL
spi_pack-0.3.4.dist-info/top_level.txt
spi_pack-0.3.4.dist-info/RECORD
